kortecx/__init__.py
kortecx/__main__.py
kortecx/py.typed
kortecx/backend/Cargo.lock
kortecx/backend/Cargo.toml
kortecx/backend/src/lib.rs
kortecx/cli/Cli.py
kortecx/cli/__init__.py
kortecx/crates/Dockerfile.dev
kortecx/crates/__init__.py
kortecx/frontend/.gitignore
kortecx/frontend/.npmrc
kortecx/frontend/.prettierignore
kortecx/frontend/.prettierrc
kortecx/frontend/README.md
kortecx/frontend/eslint.config.js
kortecx/frontend/package-lock.json
kortecx/frontend/package.json
kortecx/frontend/playwright.config.ts
kortecx/frontend/svelte.config.js
kortecx/frontend/tsconfig.json
kortecx/frontend/vite.config.ts
kortecx/frontend/vitest-setup-client.ts
kortecx/frontend/.svelte-kit/ambient.d.ts
kortecx/frontend/.svelte-kit/non-ambient.d.ts
kortecx/frontend/.svelte-kit/tsconfig.json
kortecx/frontend/.svelte-kit/generated/root.js
kortecx/frontend/.svelte-kit/generated/root.svelte
kortecx/frontend/.svelte-kit/generated/client/app.js
kortecx/frontend/.svelte-kit/generated/client/matchers.js
kortecx/frontend/.svelte-kit/generated/client/nodes/0.js
kortecx/frontend/.svelte-kit/generated/client/nodes/1.js
kortecx/frontend/.svelte-kit/generated/client/nodes/2.js
kortecx/frontend/.svelte-kit/generated/server/internal.js
kortecx/frontend/.svelte-kit/types/route_meta_data.json
kortecx/frontend/.svelte-kit/types/src/routes/$types.d.ts
kortecx/frontend/e2e/demo.test.ts
kortecx/frontend/src/app.css
kortecx/frontend/src/app.d.ts
kortecx/frontend/src/app.html
kortecx/frontend/src/demo.spec.ts
kortecx/frontend/src/lib/index.ts
kortecx/frontend/src/lib/assets/favicon.svg
kortecx/frontend/src/routes/+layout.svelte
kortecx/frontend/src/routes/+page.svelte
kortecx/frontend/src/routes/page.svelte.spec.ts
kortecx/frontend/static/robots.txt
kortecx/handlers/__init__.py
kortecx/handlers/api/__init__.py
kortecx/handlers/api/_requests_handler.py
kortecx/handlers/gdb/__init__.py
kortecx/handlers/gdb/neo4j_handler.py
kortecx/handlers/rdb/__init__.py
kortecx/handlers/rdb/duckdb_handler.py
kortecx-0.1.1.dist-info/METADATA
kortecx-0.1.1.dist-info/WHEEL
kortecx-0.1.1.dist-info/entry_points.txt
kortecx-0.1.1.dist-info/licenses/LICENSE.txt
kortecx-0.1.1.dist-info/RECORD
