Metadata-Version: 2.4
Name: kortecx
Version: 0.1.1
Summary: Executable Intelligence platform
Project-URL: homepage, https://kortecx.com
Project-URL: issues, https://github.com/kortecx/kortecx/issues
Project-URL: documentation, https://kortecx.com/docs
Project-URL: repository, https://github.com/kortecx/kortecx
Author-email: Kortecx <kortecxhelp@gmail.com>, Jay Reddy <jayachandra.s.reddy@gmail.com>
License: MIT
License-File: LICENSE.txt
Keywords: AI Workflows,Agents,ai,artificial intelligence,llm,machine learning,reinforcement learning
Classifier: Development Status :: 2 - Pre-Alpha
Classifier: Intended Audience :: Developers
Classifier: Intended Audience :: Science/Research
Classifier: License :: OSI Approved :: MIT License
Classifier: Programming Language :: Python :: 3.10
Classifier: Topic :: Scientific/Engineering :: Artificial Intelligence
Classifier: Topic :: Software Development :: Libraries :: Python Modules
Requires-Python: >=3.10
Requires-Dist: accelerate>=1.11.0
Requires-Dist: click>=8.3.0
Requires-Dist: diffusers>=0.35.2
Requires-Dist: duckdb>=1.4.1
Requires-Dist: maturin>=1.9.6
Requires-Dist: mlflow>=3.5.1
Requires-Dist: neo4j>=6.0.2
Requires-Dist: onnx>=1.19.1
Requires-Dist: peft>=0.17.1
Requires-Dist: protobuf>=6.33.0
Requires-Dist: qdrant-client>=1.15.1
Requires-Dist: torch>=2.9.0
Requires-Dist: torchaudio>=2.9.0
Requires-Dist: torchvision>=0.24.0
Requires-Dist: transformers>=4.57.1
Requires-Dist: trl>=0.24.0
